{
  "kind": "collectionType",
  "collectionName": "orders",
  "info": {
    "name": "orders",
    "description": ""
  },
  "options": {
    "increments": true,
    "timestamps": true,
    "draftAndPublish": true
  },
  "attributes": {
    "amount": {
      "type": "decimal"
    },
    "fullname": {
      "type": "string",
      "required": true
    },
    "products": {
      "type": "json",
      "required": true
    },
    "additional": {
      "type": "string",
      "required": true
    },
    "phone": {
      "type": "string",
      "required": true
    }
  }
}
